{
  "TranslationProperties": {
    "Name": "Beskar Ingot"
  },
  "Categories": [
    "Items.Ingredients"
  ],
  "Recipe": {
    "Input": [
      {
        "ItemId": "Ore_Iron",
        "Quantity": 1
      }
    ],
    "BenchRequirement": [
      {
        "Type": "Processing",
        "Id": "Furnace"
      }
    ],
    "OutputQuantity": 1,
    "TimeSeconds": 14
  },
  "Model": "Resources/ItemModels/Beskar_Bar.blockymodel",
  "Texture": "Resources/ItemTextures/Beskar_Bar_Texture.png",
  "Icon": "Icons/ItemsGenerated/OrbisGalactic_Bar_Beskar.png",
  "ResourceTypes": [
    {
      "Id": "Metal_Bars"
    }
  ],
  "PlayerAnimationsId": "Item",
  "IconProperties": {
    "Scale": 1,
    "Rotation": [
      22.5,
      45,
      22.5
    ],
    "Translation": [
      0,
      -3
    ]
  },
  "Tags": {
    "Type": [
      "Ingredient"
    ]
  },
  "ItemEntity": {
    "ParticleSystemId": null
  },
  "ItemSoundSetId": "ISS_Items_Ingots",
  "DropOnDeath": true
}
