{
  "Model": "Items/Ingredients/Holocron/HolocronCore.blockymodel",
  "Texture": "Items/Ingredients/Holocron/HolocronCore_Texture.png",
  "Categories": [
    "OrbisGalactic.Ingredients"
  ],
  "TranslationProperties": {
    "Name": "Holocron Core",
    "Description": "A new holocron core used for fixing a broken holocron."
  },
  "UsePlayerAnimations": true,
  "PlayerAnimationsId": "Item",
  "Scale": 1,
  "Icon": "Icons/ItemsGenerated/OrbisGalactic_HolocronCore.png",
  "IconProperties": {
    "Scale": 1,
    "Rotation": [
      272,
      140,
      29
    ],
    "Translation": [
      2,
      -1
    ]
  },
  "ItemSoundSetId": "ISS_Items_Gems",
  "Quality": "Rare"
}
